{
  "Theme": {
    "Color": {
      "Primary": {
        "50": {
          "value": "#B3ECFF",
          "type": "color"
        },
        "100": {
          "value": "#80DFFF",
          "type": "color"
        },
        "200": {
          "value": "#4CD3FF",
          "type": "color"
        },
        "300": {
          "value": "#1AC6FF",
          "type": "color"
        },
        "400": {
          "value": "#00ADE6",
          "type": "color"
        },
        "500": {
          "value": "#0086B2",
          "type": "color"
        },
        "600": {
          "value": "#006080",
          "type": "color"
        },
        "700": {
          "value": "#003A4D",
          "type": "color"
        },
        "800": {
          "value": "#002633",
          "type": "color"
        },
        "900": {
          "value": "#00131A",
          "type": "color"
        }
      },
      "Background": {
        "Primary": {
          "value": "{Foundation.Color.Neutral.50}",
          "type": "color"
        },
        "Menu": {
          "value": "{Theme.Color.Primary.400}",
          "type": "color"
        },
        "Action": {
          "Default": {
            "value": "{Theme.Color.Primary.400}",
            "type": "color"
          },
          "Hover": {
            "value": "{Theme.Color.Primary.500}",
            "type": "color"
          },
          "Active": {
            "value": "{Theme.Color.Primary.500}",
            "type": "color"
          }
        }
      },
      "Text": {
        "Regular": {
          "value": "{Foundation.Color.Neutral.900}",
          "type": "color"
        },
        "Muted": {
          "value": "{Foundation.Color.Neutral.500}",
          "type": "color"
        }
      },
      "UI": {
        "Border": {
          "value": "{Foundation.Color.Neutral.200}",
          "type": "color"
        }
      }
    },
    "Typography": {
      "Font family": {
        "Sans serif": {
          "value": "Inter",
          "type": "fontFamilies"
        }
      },
      "Font weight": {
        "Regular": {
          "value": "Regular",
          "type": "fontWeights"
        },
        "Semibold": {
          "value": "Semi Bold",
          "type": "fontWeights"
        }
      }
    }
  }
}